socat_lib/__init__.py
socat_lib/core.py
socatlib-2.0.1.dist-info/METADATA
socatlib-2.0.1.dist-info/WHEEL
socatlib-2.0.1.dist-info/top_level.txt
socatlib-2.0.1.dist-info/RECORD
